srv6_tracert/__init__.py
srv6_tracert-0.0.7.data/scripts/srv6_traceroute.py
srv6_tracert-0.0.7.dist-info/LICENSE.md
srv6_tracert-0.0.7.dist-info/METADATA
srv6_tracert-0.0.7.dist-info/WHEEL
srv6_tracert-0.0.7.dist-info/top_level.txt
srv6_tracert-0.0.7.dist-info/RECORD
